README.rst
environconfig.py
setup.py
environconfig.egg-info/PKG-INFO
environconfig.egg-info/SOURCES.txt
environconfig.egg-info/dependency_links.txt
environconfig.egg-info/not-zip-safe
environconfig.egg-info/top_level.txt