Metadata-Version: 1.1
Name: environconfig
Version: 1.7.0
Summary: Application configuration from environment variables made easy
Home-page: https://github.com/buguroo/environconfig
Author: Roberto Abdelkader Martínez Pérez
Author-email: robertomartinezp@gmail.com
License: LGPLv3
Keywords: environment variables configuration
Platform: UNKNOWN
Classifier: Development Status :: 4 - Beta
Classifier: Programming Language :: Python :: 3.4
Classifier: Programming Language :: Python :: 3.5
Classifier: Programming Language :: Python :: 3.6
